sparkcraft/__init__.py
sparkcraft/joins.py
sparkcraft/partitions.py
sparkcraft/utils/__init__.py
sparkcraft/utils/session.py
sparkcraft/utils/size_estimation.py
sparkcraft-0.0.4.dist-info/LICENSE
sparkcraft-0.0.4.dist-info/METADATA
sparkcraft-0.0.4.dist-info/WHEEL
sparkcraft-0.0.4.dist-info/entry_points.txt
sparkcraft-0.0.4.dist-info/RECORD
