Metadata-Version: 2.1
Name: sparkcraft
Version: 0.0.4
Summary: SparkCraft
Home-page: https://github.com/MichaelisTrofficus/sparkcraft
License: MIT
Author: Miguel Otero Pedrido
Author-email: miguel.otero.pedrido.1993@gmail.com
Requires-Python: >=3.9,<4.0
Classifier: Development Status :: 3 - Alpha
Classifier: License :: OSI Approved :: MIT License
Classifier: Programming Language :: Python :: 3
Classifier: Programming Language :: Python :: 3.9
Classifier: Programming Language :: Python :: 3.10
Classifier: Programming Language :: Python :: 3.11
Requires-Dist: pyspark (>=3.4.1,<4.0.0)
Project-URL: Changelog, https://github.com/MichaelisTrofficus/sparkcraft/releases
Project-URL: Documentation, https://sparkcraft.readthedocs.io
Project-URL: Repository, https://github.com/MichaelisTrofficus/sparkcraft
